django_dynamictexts-0.2.2.dist-info/licenses/LICENSE
texts/__init__.py
texts/admin.py
texts/apps.py
texts/models.py
texts/translation.py
texts/migrations/0001_initial.py
texts/migrations/0002_dynamictext_content_en_dynamictext_content_lv_and_more.py
texts/migrations/__init__.py
texts/templatetags/__init__.py
texts/templatetags/dynamictexts_tags.py
django_dynamictexts-0.2.2.dist-info/METADATA
django_dynamictexts-0.2.2.dist-info/WHEEL
django_dynamictexts-0.2.2.dist-info/top_level.txt
django_dynamictexts-0.2.2.dist-info/RECORD
