Metadata-Version: 2.4
Name: django-dynamictexts
Version: 0.2.2
Summary: Reusable Django app for dynamic multilingual texts with template tags.
Home-page: https://git.tormaks.com/basistaplay/django-dynamictexts
Author: BasistaPlay
Author-email: basistaplay@gmail.com
License: MIT
Classifier: Framework :: Django
Classifier: Programming Language :: Python :: 3
Classifier: License :: OSI Approved :: MIT License
Classifier: Operating System :: OS Independent
License-File: LICENSE
Requires-Dist: Django>=4.2
Requires-Dist: django-modeltranslation>=0.17
Dynamic: author
Dynamic: author-email
Dynamic: classifier
Dynamic: description
Dynamic: description-content-type
Dynamic: home-page
Dynamic: license
Dynamic: license-file
Dynamic: requires-dist
Dynamic: summary
